momo_psb/__init__.py
momo_psb/api.py
momo_psb/py.typed
momo_psb-0.1.0.dist-info/METADATA
momo_psb-0.1.0.dist-info/WHEEL
momo_psb-0.1.0.dist-info/licenses/LICENSE
momo_psb-0.1.0.dist-info/RECORD
