Metadata-Version: 2.4
Name: momo-psb
Version: 0.1.0
Summary: A Python SDK for integrating with the MTN MoMo API (Payment Service Bank)
Author-email: Ifeanyi Nneji <ifeanyinneji777@gmail.com>
License: MIT License
License-File: LICENSE
Keywords: API,MTN,MoMo,Mobile Money,Payment,Python,SDK
Classifier: Development Status :: 4 - Beta
Classifier: Intended Audience :: Developers
Classifier: License :: OSI Approved :: MIT License
Classifier: Programming Language :: Python :: 3
Classifier: Programming Language :: Python :: 3.12
Classifier: Topic :: Internet
Classifier: Topic :: Software Development :: Libraries :: Python Modules
Requires-Python: >=3.12
Requires-Dist: requests>=2.25.1
